odoo/addons/brand_stock_account/README.rst
odoo/addons/brand_stock_account/__init__.py
odoo/addons/brand_stock_account/__manifest__.py
odoo/addons/brand_stock_account/i18n/brand_stock_account.pot
odoo/addons/brand_stock_account/models/__init__.py
odoo/addons/brand_stock_account/models/account_move.py
odoo/addons/brand_stock_account/readme/CONFIGURE.rst
odoo/addons/brand_stock_account/readme/CONTRIBUTORS.rst
odoo/addons/brand_stock_account/readme/DESCRIPTION.rst
odoo/addons/brand_stock_account/static/description/icon.png
odoo/addons/brand_stock_account/static/description/index.html
odoo/addons/brand_stock_account/tests/__init__.py
odoo/addons/brand_stock_account/tests/test_account_move.py
odoo13_addon_brand_stock_account-13.0.1.0.2.dev4.dist-info/METADATA
odoo13_addon_brand_stock_account-13.0.1.0.2.dev4.dist-info/WHEEL
odoo13_addon_brand_stock_account-13.0.1.0.2.dev4.dist-info/top_level.txt
odoo13_addon_brand_stock_account-13.0.1.0.2.dev4.dist-info/RECORD
