Metadata-Version: 2.1
Name: odoo13-addon-brand-stock-account
Version: 13.0.1.0.2.dev4
Summary: When the account entry is generated by the stock move, fill also the brand.
Home-page: https://github.com/OCA/brand
Author: ACSONE SA/NV,Odoo Community Association (OCA)
Author-email: support@odoo-community.org
License: AGPL-3
Platform: UNKNOWN
Classifier: Programming Language :: Python
Classifier: Framework :: Odoo
Classifier: Framework :: Odoo :: 13.0
Classifier: License :: OSI Approved :: GNU Affero General Public License v3
Classifier: Development Status :: 4 - Beta
Requires-Python: >=3.5
Requires-Dist: odoo13-addon-account-brand
Requires-Dist: odoo13-addon-sale-brand
Requires-Dist: odoo <13.1dev,>=13.0a
